template_ml_model/__about__.py
template_ml_model/__init__.py
template_ml_model/config.py
template_ml_model/model.py
template_ml_model/predict.py
template_ml_model/train.py
template_ml_model/training_launcher.py
template_ml_model/utils.py
template_ml_model-0.3.0.dist-info/METADATA
template_ml_model-0.3.0.dist-info/WHEEL
template_ml_model-0.3.0.dist-info/entry_points.txt
template_ml_model-0.3.0.dist-info/RECORD
